autobuild/__init__.py
autobuild/archive_utils.py
autobuild/autobuild_base.py
autobuild/autobuild_main.py
autobuild/autobuild_tool_build.py
autobuild/autobuild_tool_configure.py
autobuild/autobuild_tool_edit.py
autobuild/autobuild_tool_graph.py
autobuild/autobuild_tool_install.py
autobuild/autobuild_tool_installables.py
autobuild/autobuild_tool_manifest.py
autobuild/autobuild_tool_package.py
autobuild/autobuild_tool_print.py
autobuild/autobuild_tool_source_environment.py
autobuild/autobuild_tool_uninstall.py
autobuild/build_id.py
autobuild/common.py
autobuild/configfile.py
autobuild/executable.py
autobuild/hash_algorithms.py
autobuild/interactive.py
autobuild/update.py
autobuild/version.py
autobuild/scm/__init__.py
autobuild/scm/base.py
autobuild/scm/git.py
autobuild-3.10.1.dist-info/licenses/LICENSE
tests/executables/__init__.py
tests/executables/echo.py
tests/executables/envtest.py
tests/executables/noop.py
autobuild-3.10.1.dist-info/METADATA
autobuild-3.10.1.dist-info/WHEEL
autobuild-3.10.1.dist-info/entry_points.txt
autobuild-3.10.1.dist-info/top_level.txt
autobuild-3.10.1.dist-info/RECORD
